[
  {
    "id": "5d2c865e9a0bae79a6ef7cfa",
    "code": "KLS580",
    "description": "Passport",
    "agency": "KLS",
    "orderDate": "30.12.2020",
    "status": "In progress",
    "color": "danger",
    "comments": "warning",
    "orderSum": "50",
    "symbols": "12050",
    "pages": "12.14",
    "language": "CN-UA",
    "finishTime": "04.09.2020",
    "hasReport":true
  },
  {
    "id": "5d2c865e9a0bae79a6ef7cfb",
    "code": "TRS875",
    "description": "Personal",
    "agency": "TRIS",
    "orderDate": "06.08.2019",
    "status": "Finished",
    "color": "primary",
    "comments": "warning",
    "orderSum": "842",
    "symbols": "12050",
    "pages": "12.14",
    "language": "CN-RU",
    "finishTime": "11.03.2020",
    "hasReport":true
  },
  {
    "id": "5d2c865e9a0bae79a6ef7cfc",
    "code": "ADR879",
    "description": "Owner data",
    "agency": "Adrenaline 23",
    "orderDate": "05.05.2020",
    "status": "Proofreading",
    "comments": "warning",
    "color": "secondary",
    "orderSum": "789",
    "symbols": "12050",
    "pages": "12.14",
    "language": "ZH-RU",
    "finishTime": "12.02.2020",
    "hasReport":true
  },
  {
    "id": "5d2c865e9a0bae79a6ef7cfc",
    "code": "ADR879",
    "description": "Owner data",
    "agency": "Adrenaline 23",
    "orderDate": "05.05.2020",
    "status": "Editing",
    "comments": "warning",
    "color": "secondary",
    "orderSum": "789",
    "symbols": "12050",
    "pages": "12.14",
    "language": "EN-UA",
    "finishTime": "24.08.2020",
    "hasReport":true
  },
  {
    "id": "5d2c865e9a0bae79a6ef7cfd",
    "code": "KBP328",
    "description": "Drawings",
    "agency": "Kyiv Translation Buro",
    "orderDate": "01.09.2020",
    "status": "Paid",
    "color": "gray",
    "comments": "warning",
    "orderSum": "1223",
    "symbols": "12050",
    "pages": "12.14",
    "language": "EN-RU",
    "finishTime": "01.07.2020",
    "hasReport":true
  }
]
